{
  "id": "nezumi0627",
  "pinHash": "8f85d66000972c4a741f930c122227e60fee5c453d7e1b373e229834f76e8d76",
  "updatedAt": 1783881191643,
  "state": {
    "owned": {},
    "defeatedBosses": {},
    "unlockedNpcs": {},
    "completedEvents": {},
    "visitedBiomes": {},
    "builtStations": {},
    "craftedItems": {},
    "collected": {},
    "goals": [],
    "favorites": {},
    "recentSearches": [],
    "recentViews": [],
    "dailyTasks": [],
    "dailyDate": "2026-07-12",
    "dailyChecked": {},
    "theme": "dark",
    "notifications": true
  }
}